task_queue_checker/__init__.py
task_queue_checker/base.py
task_queue_checker/task_queue_checker.py
task_queue_checker/types.py
task_queue_checker/utils.py
task_queue_checker/storage/__init__.py
task_queue_checker/storage/persist_queue_mysql.py
task_queue_checker/storage/persist_queue_postgres.py
task_queue_checker/storage/persist_queue_redis.py
task_queue_checker/storage/persist_queue_sqlite.py
task_queue_checker-0.0.5.dist-info/METADATA
task_queue_checker-0.0.5.dist-info/WHEEL
task_queue_checker-0.0.5.dist-info/licenses/LICENSE
task_queue_checker-0.0.5.dist-info/RECORD
