Metadata-Version: 2.4
Name: task-queue-checker
Version: 0.0.5
Summary: Tool designed to simplify the management and monitoring of task queues in Python environments
Project-URL: Homepage, https://github.com/raulodev/task-queue-checker
Project-URL: Issues, https://github.com/raulodev/task-queue-checker/issues
Author-email: Raúl Cobiellas <raulodev@gmail.com>
License-File: LICENSE
Classifier: License :: OSI Approved :: MIT License
Classifier: Operating System :: OS Independent
Classifier: Programming Language :: Python :: 3
Requires-Python: >=3.8
